blendedUx/__init__.py
blendedUx/blended_django/__init__.py
blendedUx/blended_django/blended_django_app/__init__.py
blendedUx/blended_django/blended_django_app/admin.py
blendedUx/blended_django/blended_django_app/context.py
blendedUx/blended_django/blended_django_app/functions.py
blendedUx/blended_django/blended_django_app/helpers.py
blendedUx/blended_django/blended_django_app/models.py
blendedUx/blended_django/blended_django_app/tests.py
blendedUx/blended_django/blended_django_app/transform.py
blendedUx/blended_django/blended_django_app/urls.py
blendedUx/blended_django/blended_django_app/views.py
blendedUx/blended_django/blended_django_app/migrations/__init__.py
blendedUx/blended_django/blended_hostlib/__init__.py
blendedUx/blended_django/blended_hostlib/initializer.py
blendedUx/blended_django/blended_hostlib/tests.py
blendedUx/blended_django/blended_hostlib/transform_image.py
blendedUx/blended_django/blended_hostlib/backend/__init__.py
blendedUx/blended_django/blended_hostlib/backend/backend.py
blendedUx/blended_django/blended_hostlib/backend/intermediary.py
blendedUx/blended_django/blended_hostlib/backend/settings.py
blendedUx/blended_django/blended_hostlib/controller/__init__.py
blendedUx/blended_django/blended_hostlib/controller/controller.py
blendedUx/blended_django/blended_hostlib/exceptions/__init__.py
blendedUx/blended_django/blended_hostlib/exceptions/exceptions.py
blendedUx/blended_django/blended_hostlib/functions/__init__.py
blendedUx/blended_django/blended_hostlib/functions/functions.py
blendedUx/blended_django/blended_hostlib/network/__init__.py
blendedUx/blended_django/blended_hostlib/network/network.py
blendedUx/blended_django/blended_hostlib/network/settings.py
blendedUx/blended_django/blended_hostlib/swagger_client/__init__.py
blendedUx/blended_django/blended_hostlib/swagger_client/api_client.py
blendedUx/blended_django/blended_hostlib/swagger_client/configuration.py
blendedUx/blended_django/blended_hostlib/swagger_client/rest.py
blendedux-0.1.4.dist-info/LICENSE
blendedux-0.1.4.dist-info/METADATA
blendedux-0.1.4.dist-info/WHEEL
blendedux-0.1.4.dist-info/top_level.txt
blendedux-0.1.4.dist-info/RECORD
