Metadata-Version: 2.1
Name: blendedux
Version: 0.1.4
Summary: A cross-platform design theme framework.
Home-page: UNKNOWN
Author: Himanshu
Author-email: <hbhadu@cognam.com>
License: UNKNOWN
Platform: UNKNOWN
Requires-Dist: certifi ==2022.5.18.1
Requires-Dist: click ==8.1.3
Requires-Dist: colorama ==0.4.6
Requires-Dist: Flask ==2.2.3
Requires-Dist: itsdangerous ==2.1.2
Requires-Dist: Jinja2 ==3.1.2
Requires-Dist: MarkupSafe ==2.1.2
Requires-Dist: Pillow ==9.5.0
Requires-Dist: python-dateutil ==2.8.2
Requires-Dist: six ==1.16.0
Requires-Dist: urllib3 ==1.26.15
Requires-Dist: Werkzeug ==2.2.3
Requires-Dist: blinker ==1.6.2
Requires-Dist: blendedUx-Lang ==1.1.2
